{
  "hash": "d13ee012c4e7a8a762f61cd22e565092",
  "result": {
    "engine": "knitr",
    "markdown": "# Load Packages\n\n\n::: {.cell}\n\n:::\n\n::: {.cell}\n\n:::\n\n\n# Load data\n\n\n\n::: {.cell}\n\n:::\n\n\n\n# Add calculated values to raw clinician tracker data\n\n\n::: {.cell}\n\n:::\n\n::: {.cell}\n\n:::\n\n\n\n# Save data\n\n\n::: {.cell}\n\n:::",
    "supporting": [],
    "filters": [
      "rmarkdown/pagebreak.lua"
    ],
    "includes": {},
    "engineDependencies": {},
    "preserve": {},
    "postProcess": true
  }
}